wagtail_localize_smartling/__init__.py
wagtail_localize_smartling/admin_urls.py
wagtail_localize_smartling/apps.py
wagtail_localize_smartling/checks.py
wagtail_localize_smartling/components.py
wagtail_localize_smartling/constants.py
wagtail_localize_smartling/exceptions.py
wagtail_localize_smartling/forms.py
wagtail_localize_smartling/models.py
wagtail_localize_smartling/settings.py
wagtail_localize_smartling/signal_handlers.py
wagtail_localize_smartling/signals.py
wagtail_localize_smartling/sync.py
wagtail_localize_smartling/utils.py
wagtail_localize_smartling/views.py
wagtail_localize_smartling/viewsets.py
wagtail_localize_smartling/wagtail_hooks.py
wagtail_localize_smartling/api/__init__.py
wagtail_localize_smartling/api/client.py
wagtail_localize_smartling/api/serializers.py
wagtail_localize_smartling/api/types.py
wagtail_localize_smartling/management/__init__.py
wagtail_localize_smartling/management/commands/__init__.py
wagtail_localize_smartling/management/commands/populate_smartling_job_hashes.py
wagtail_localize_smartling/management/commands/sync_smartling.py
wagtail_localize_smartling/migrations/0001_initial.py
wagtail_localize_smartling/migrations/0002_job_content_hash.py
wagtail_localize_smartling/migrations/0003_data_add_translation_approver_auth_group.py
wagtail_localize_smartling/migrations/0004_landedtranslationtask.py
wagtail_localize_smartling/migrations/0005_jobtranslation.py
wagtail_localize_smartling/migrations/0006_populate_jobtranslation.py
wagtail_localize_smartling/migrations/0007_job_translations_through.py
wagtail_localize_smartling/migrations/0008_jobtranslation_content_hash.py
wagtail_localize_smartling/migrations/__init__.py
wagtail_localize_smartling/templates/wagtail_localize/admin/edit_translation.html
wagtail_localize_smartling/templates/wagtail_localize_smartling/admin/edit_translation_message.html
wagtail_localize_smartling/templates/wagtail_localize_smartling/admin/job_report.html
wagtail_localize_smartling-0.11.0.dist-info/licenses/LICENSE
wagtail_localize_smartling-0.11.0.dist-info/WHEEL
wagtail_localize_smartling-0.11.0.dist-info/METADATA
wagtail_localize_smartling-0.11.0.dist-info/RECORD
