Metadata-Version: 2.4
Name: wagtail-localize-smartling
Version: 0.11.0
Summary: An extension for wagtail-localize that integrates with the Smartling translation platform
Author-email: Ben Dickinson <ben.dickinson@torchbox.com>
Maintainer-email: Steve Jalim <opensource@stevejalim.mozmail.com>
Requires-Python: >=3.11
Classifier: Development Status :: 2 - Pre-Alpha
Classifier: Intended Audience :: Developers
Classifier: License :: OSI Approved :: Mozilla Public License 2.0 (MPL 2.0)
Classifier: Natural Language :: English
Classifier: Operating System :: OS Independent
Classifier: Programming Language :: Python
Classifier: Programming Language :: Python :: 3
Classifier: Programming Language :: Python :: 3.13
Classifier: Framework :: Django
Classifier: Framework :: Django :: 5.1
Classifier: Framework :: Django :: 5.2
Classifier: Framework :: Django :: 6.0
Classifier: Framework :: Wagtail
Classifier: Framework :: Wagtail :: 6
Classifier: Framework :: Wagtail :: 7
License-File: LICENSE
Requires-Dist: Django>=5.1
Requires-Dist: Wagtail>=6.1
Requires-Dist: djangorestframework>=3
Requires-Dist: requests
Requires-Dist: wagtail-localize>=1.0.0
Requires-Dist: beautifulsoup4==4.12.3 ; extra == "test"
Requires-Dist: coverage>=7.6.1,<8.0 ; extra == "test"
Requires-Dist: dj-database-url==2.1.0 ; extra == "test"
Requires-Dist: django-stubs ; extra == "test"
Requires-Dist: djangorestframework-stubs ; extra == "test"
Requires-Dist: freezegun==1.5.1 ; extra == "test"
Requires-Dist: pre-commit==3.4.0 ; extra == "test"
Requires-Dist: pyright==1.1.390 ; extra == "test"
Requires-Dist: pytest-cov==5.0.0 ; extra == "test"
Requires-Dist: pytest-django==4.8.0 ; extra == "test"
Requires-Dist: pytest-mock==3.14.0 ; extra == "test"
Requires-Dist: pytest-responses==0.5.1 ; extra == "test"
Requires-Dist: pytest-xdist==3.6.1 ; extra == "test"
Requires-Dist: pytest==8.3.2 ; extra == "test"
Requires-Dist: python-dotenv==1.0.1 ; extra == "test"
Requires-Dist: responses==0.25.0 ; extra == "test"
Requires-Dist: ruff==0.14.14 ; extra == "test"
Requires-Dist: tox ; extra == "test"
Requires-Dist: tox-gh-actions ; extra == "test"
Requires-Dist: wagtail-factories==4.2.1 ; extra == "test"
Project-URL: Changelog, https://github.com/mozilla/wagtail-localize-smartling/blob/main/CHANGELOG.md
Project-URL: Issues, https://github.com/mozilla/wagtail-localize-smartling/issues
Project-URL: Repository, https://github.com/mozilla/wagtail-localize-smartling
Provides-Extra: test
